<?xml version="1.0" encoding="ISO-8859-15"?>

<BOLSAS-ANO xmlns:xsi="http://www.w3.org/2001/XMLSchema-instance" DATA-ATUALIZACAO="06012018" HORA-ATUALIZACAO="051023" FORMATO-DATA-ATUALIZACAO="DDMMAAAA" FORMATO-HORA-ATUALIZACAO="HHMMSS" xsi:noNamespaceSchemaLocation="hst_pgt_bolsas_cnpq_2017.xsd">
  <BOLSA>
    <ANO-PAGAMENTO>2017</ANO-PAGAMENTO>
    <NRO-ID-CNPQ>0489923739990813</NRO-ID-CNPQ>
    <NOME-COMPLETO>Alicy Daliane de Melo</NOME-COMPLETO>
    <SEXO>F</SEXO>
    <PAIS-NASCIMENTO>Brasil</PAIS-NASCIMENTO>
    <CODIGO-DO-PROCESSO>100001/2017-3</CODIGO-DO-PROCESSO>
    <MODALIDADE-DO-PROCESSO>Iniciação ao Extensionismo</MODALIDADE-DO-PROCESSO>
    <CATEGORIA-NIVEL-DA-MODALIDADE>NI</CATEGORIA-NIVEL-DA-MODALIDADE>
    <DATA-INICIO-PROCESSO>01/01/2017</DATA-INICIO-PROCESSO>
    <DATA-TERMINO-PROCESSO>28/02/2017</DATA-TERMINO-PROCESSO>
    <TITULO-DO-PROCESSO>SEMENTES CRIOULAS PARA O FORTALECIMENTO DA AGRICULTURA FAMILIAR NO VALE DO ACU –RN</TITULO-DO-PROCESSO>
    <QUANTIDADE-MESES-PAGOS>2.00</QUANTIDADE-MESES-PAGOS>
    <VALOR-PAGO>720.00</VALOR-PAGO>
    <MOEDA>REAL</MOEDA>
    <NOME-INSTITUICAO>Instituto Federal de Educação, Ciência e Tecnologia do Rio Grande do Norte</NOME-INSTITUICAO>
    <SIGLA-INSTITUICAO>IFRN</SIGLA-INSTITUICAO>
    <PAIS-INSTITUICAO>Brasil</PAIS-INSTITUICAO>
    <SIGLA-UF-INSTITUICAO>RN</SIGLA-UF-INSTITUICAO>
    <NATUREZA-JURIDICA>Autarquia Federal</NATUREZA-JURIDICA>
    <NIVEL-DO-CURSO xsi:nil="true"></NIVEL-DO-CURSO>
    <NOME-CURSO xsi:nil="true"></NOME-CURSO>
    <NOME-GRANDE-AREA-DO-CONHECIMENTO>Ciências Agrárias</NOME-GRANDE-AREA-DO-CONHECIMENTO>
    <NOME-DA-AREA-DO-CONHECIMENTO>Agronomia</NOME-DA-AREA-DO-CONHECIMENTO>
    <NOME-DA-SUB-AREA-DO-CONHECIMENTO>Fitotecnia</NOME-DA-SUB-AREA-DO-CONHECIMENTO>
    <NOME-DA-ESPECIALIDADE>Produção e Beneficiamento de Sementes</NOME-DA-ESPECIALIDADE>
    <QUANTIDADE-BOLSA-ANO>0.18</QUANTIDADE-BOLSA-ANO>
  </BOLSA>
  <BOLSA>
    <ANO-PAGAMENTO>2017</ANO-PAGAMENTO>
    <NRO-ID-CNPQ>4715501265431682</NRO-ID-CNPQ>
    <NOME-COMPLETO>Mônika Maria Gomes Costa</NOME-COMPLETO>
    <SEXO>F</SEXO>
    <PAIS-NASCIMENTO>Brasil</PAIS-NASCIMENTO>
    <CODIGO-DO-PROCESSO>386219/2014-1</CODIGO-DO-PROCESSO>
    <MODALIDADE-DO-PROCESSO>Desenvolvimento Tecnonógico Industrial</MODALIDADE-DO-PROCESSO>
    <CATEGORIA-NIVEL-DA-MODALIDADE>B</CATEGORIA-NIVEL-DA-MODALIDADE>
    <DATA-INICIO-PROCESSO>01/01/2015</DATA-INICIO-PROCESSO>
    <DATA-TERMINO-PROCESSO>31/01/2017</DATA-TERMINO-PROCESSO>
    <TITULO-DO-PROCESSO>Determinantes ao longo do ciclo vital da obesidade precursores de doencas cronicas capital humano e saude mental</TITULO-DO-PROCESSO>
    <QUANTIDADE-MESES-PAGOS>1.00</QUANTIDADE-MESES-PAGOS>
    <VALOR-PAGO>3000.00</VALOR-PAGO>
    <MOEDA>REAL</MOEDA>
    <NOME-INSTITUICAO>Universidade Federal de Pelotas</NOME-INSTITUICAO>
    <SIGLA-INSTITUICAO>UFPEL</SIGLA-INSTITUICAO>
    <PAIS-INSTITUICAO>Brasil</PAIS-INSTITUICAO>
    <SIGLA-UF-INSTITUICAO>RS</SIGLA-UF-INSTITUICAO>
    <NATUREZA-JURIDICA>Fundação Federal</NATUREZA-JURIDICA>
    <NIVEL-DO-CURSO xsi:nil="true"></NIVEL-DO-CURSO>
    <NOME-CURSO xsi:nil="true"></NOME-CURSO>
    <NOME-GRANDE-AREA-DO-CONHECIMENTO>Ciências da Saúde</NOME-GRANDE-AREA-DO-CONHECIMENTO>
    <NOME-DA-AREA-DO-CONHECIMENTO>Saúde Coletiva</NOME-DA-AREA-DO-CONHECIMENTO>
    <NOME-DA-SUB-AREA-DO-CONHECIMENTO>Epidemiologia</NOME-DA-SUB-AREA-DO-CONHECIMENTO>
    <NOME-DA-ESPECIALIDADE>Não informado</NOME-DA-ESPECIALIDADE>
    <QUANTIDADE-BOLSA-ANO>0.09</QUANTIDADE-BOLSA-ANO>
  </BOLSA>
</BOLSAS-ANO>
